stream_arbiter.sv
module stream_arbiter #(
  parameter   T_DATA_WIDTH = 8,
              T_QOS__WIDTH = 4,
              STREAM_COUNT = 2,
              T_ID___WIDTH = $clog2(STREAM_COUNT)
)(
  input  logic                     clk,
  input  logic                     rst_n,
  // input streams
  input  logic [T_DATA_WIDTH-1:0]  s_data_i  [STREAM_COUNT-1:0],
  input  logic [T_QOS__WIDTH-1:0]  s_qos_i   [STREAM_COUNT-1:0],
  input  logic [STREAM_COUNT-1:0]  s_last_i,
  input  logic [STREAM_COUNT-1:0]  s_valid_i,
  output logic [STREAM_COUNT-1:0]  s_ready_o,
  // output stream
  output logic [T_DATA_WIDTH-1:0]  m_data_o,
  output logic [T_QOS__WIDTH-1:0]  m_qos_o,
  output logic [T_ID___WIDTH-1:0]  m_id_o,
  output logic                     m_last_o,
  output logic                     m_valid_o,
  input  logic                     m_ready_i
);
  
  logic [1:0]  qos_i, qos_i_d;
  
  prior i_prior(.*);
  
  enum logic [1:0]
  {
    IDLE    = 2'b00,
    BCAST   = 2'b01,
    RRBCAST = 2'b10,
    FRBCAST = 2'b11
  } state;
  
  //FSM
  always_ff @(posedge clk)
    if    (!rst_n)
    begin
      state <= IDLE;
    end
    else
    begin
      case(state)
      IDLE:
        if      (qos_i == 2'b11 & m_ready_i)
          state <= RRBCAST;
        else if (qos_i != 2'b0 & m_ready_i)
          state <= BCAST;
      
      RRBCAST:
        if  (s_last_i[0] & s_ready_o[0] & s_valid_i[0])
          state <= FRBCAST;
      
      FRBCAST:
        if  (s_last_i[1] & s_ready_o[1] & s_valid_i[1])
          state <= IDLE;
      
      BCAST:
        if  ((s_last_i[0] & s_ready_o[0] & s_valid_i[0]) | (s_last_i[1] & s_ready_o[1] & s_valid_i[1]))
          state <= IDLE;
      endcase
    end
  
  //Register transfer
  always_ff @(posedge clk)
    if  (!rst_n)
    begin
      m_valid_o <= '0;
      m_last_o  <= '0;
      m_id_o    <= '0;
      m_qos_o   <= '0;
      m_data_o  <= '0;
    end
    else
    begin
      m_valid_o <= s_valid_i[0] | s_valid_i[1];
      m_last_o  <= s_last_i[0]  | s_last_i[1];
      
      case(state)
        IDLE:
        begin
          qos_i_d <= qos_i;
        
          if      (qos_i == 2'b11)
          begin
            m_id_o    <= 1'b0;
            m_qos_o   <= s_qos_i[0];
            m_data_o  <= s_data_i[0];
          end
          else
          begin
            if (qos_i == 2'b01)
            begin
              m_id_o    <= 1'b0;
              m_qos_o   <= s_qos_i[0];
              m_data_o  <= s_data_i[0];
            end
            
            if (qos_i == 2'b10)
            begin
              m_id_o    <= 1'b1;
              m_qos_o   <= s_qos_i[1];
              m_data_o  <= s_data_i[1];
            end
          end
          
        end
        
        RRBCAST:
        begin
          m_data_o <= s_data_i[0];
        end
        
        FRBCAST:
        begin
          m_data_o <= s_data_i[1];
          m_qos_o  <= s_qos_i[1];
          m_id_o   <= 1;
        end
        
        BCAST:
        begin
          
          if      (s_last_i[0] | s_last_i[1])
            qos_i_d <= 'b0;
          
          if      (qos_i_d == 2'b01)
            m_data_o <= s_data_i[0];
          else if (qos_i_d == 2'b10)
            m_data_o <= s_data_i[1];
        end
      endcase
    end
  
  //Comb other logic
  always_comb
  begin
    case(state)
      IDLE:
      begin
        s_ready_o = 2'b0;
        
        if      (qos_i == 2'b11)
          s_ready_o = 2'b01;
        else if (qos_i == 2'b01)
          s_ready_o = 2'b01;
        else if (qos_i == 2'b10)
          s_ready_o = 2'b10;
        else
          s_ready_o = 2'b0;
      end
      
      RRBCAST:
      begin
        s_ready_o = 2'b01;
      end
      
      FRBCAST:
      begin
        s_ready_o = 2'b10;
      end
      
      BCAST:
      begin
        if      (qos_i == 2'b11)
          s_ready_o = 2'b01;
        else if (qos_i == 2'b01)
          s_ready_o = 2'b01;
        else if (qos_i == 2'b10)
          s_ready_o = 2'b10;
        else
          s_ready_o = 2'b0;
      end
    endcase
  end
    
endmodule: stream_arbiter

module prior #(
  parameter T_QOS__WIDTH = 4,  
            STREAM_COUNT = 2
)(
  input  logic [T_QOS__WIDTH-1:0] s_qos_i   [STREAM_COUNT-1:0],
  input  logic [STREAM_COUNT-1:0] s_valid_i,
  output logic [STREAM_COUNT-1:0] qos_i
);
  
  always_comb
  begin
    qos_i = 2'b0;
    
    if    ( s_valid_i[0] &  s_valid_i[1])
    begin
      if      ((s_qos_i[0] >  s_qos_i[1]) & (s_qos_i[1] != 4'b0))
      begin
        qos_i = 2'b01;
      end
      else if ((s_qos_i[0] >  s_qos_i[1]) & (s_qos_i[1] == 4'b0))
      begin
        qos_i = 2'b11;
      end
      else if ((s_qos_i[0] <  s_qos_i[1]) & (s_qos_i[0] != 4'b0))
      begin
        qos_i = 2'b10;
      end
      else if ((s_qos_i[0] <  s_qos_i[1]) & (s_qos_i[0] == 4'b0))
      begin
        qos_i = 2'b11;
      end
      else if ((s_qos_i[0] == s_qos_i[1]))
      begin
        qos_i = 2'b11;
      end
    end
  
  if    ( s_valid_i[0] & ~s_valid_i[1])
    begin
      qos_i = 2'b01;
    end
    
    if    (~s_valid_i[0] &  s_valid_i[1])
    begin
      qos_i = 2'b10;
    end
  end
  
endmodule: prior

stream_arbiter_tb.sv
module stream_arbiter_tb #(
  parameter T_DATA_WIDTH = 8,
            T_QOS__WIDTH = 4,
            STREAM_COUNT = 2,
            T_ID___WIDTH = $clog2(STREAM_COUNT)
);

  //input, output 
  logic                     clk;
  logic                     rst_n;
  logic [T_DATA_WIDTH-1:0]  s_data_i  [STREAM_COUNT-1:0];
  logic [T_QOS__WIDTH-1:0]  s_qos_i   [STREAM_COUNT-1:0];
  logic [STREAM_COUNT-1:0]  s_last_i;
  logic [STREAM_COUNT-1:0]  s_valid_i;
  logic [STREAM_COUNT-1:0]  s_ready_o;
  // output stream
  logic [T_DATA_WIDTH-1:0]  m_data_o;
  logic [T_QOS__WIDTH-1:0]  m_qos_o;
  logic [T_ID___WIDTH-1:0]  m_id_o;
  logic                     m_last_o;
  logic                     m_valid_o;
  logic                     m_ready_i;
  
  //instant
  stream_arbiter  i_stream_arbiter  (.*);
  
  //dump
  initial begin
    $dumpvars;
  end
  
  //clk and reset
  initial begin
    clk   = 0;
    forever #10 clk = ~clk;
  end
  
  //test
  initial begin
    rst_n = 1;
    #20;
    rst_n = 0;
    #20;
    rst_n = 1;
    s_data_i[0] = '0;
    s_data_i[1] = '0;
    s_qos_i[0]  = '0;
    s_qos_i[1]  = '0;
    s_last_i    = '0;
    s_valid_i   = '0;
    m_ready_i   = 1;
    #10;
    
    //task one_stream x6
    for(int i = 0; i < 6; i++)
    begin
      one_stream;
    end
    
    //task diff_qos_stream
    diff_qos_stream;
    
    //task eq_prior_stream
    eq_prior_stream;
    $finish;
  end
  
  //task single stream to the arbiter
  task one_stream;
  
  logic       str;
  logic [2:0] num_pack;
  
  str       = $urandom_range(1, 0);
  num_pack  = $urandom_range(7, 2);
  
  for (int i = 0; i <= num_pack; i++)
  begin
    if      (i == 0)
    @(posedge clk)
    begin
      s_valid_i[str]  = 1;
      s_qos_i[str]    = $urandom_range(15, 0);
      s_data_i[str]   = $urandom_range(255, 0);
    end
    else if (i != num_pack)
    @(posedge clk)
    begin
      s_data_i[str]   = $urandom_range(255, 0);
    end
    else
    @(posedge clk)
    begin
      s_data_i[str]   = $urandom_range(255, 0);
      s_last_i[str]   = 1;
    end
  end
  
  @(posedge clk)
  begin
    s_valid_i   = '0;
    s_last_i    = '0;
    s_data_i[0] = '0;
    s_data_i[1] = '0;
    s_qos_i[0]  = '0;
    s_qos_i[1]  = '0;
  end
  
  #100;
  endtask
  
  //task both flows to the arbiter
  //task with different qos
  task diff_qos_stream;
  
  for(int m = 0; m < 4; m++)
  begin
    //first stream
    for (int i = 0; i < 4; i++)
    begin
      if      (i == 0)
      @(posedge clk)
      begin
        s_valid_i[0]  = 1;
        s_data_i[0]   = $urandom_range(255, 0);
        
        s_valid_i[1]  = 1;
        s_data_i[1]   = $urandom_range(255, 0);
        
        case(m)
          0:  //qos 1st > qos 2d (next qos 1st < pre qos 2d)
          begin
            s_qos_i[0]  = 15;
            s_qos_i[1]  = 13;
          end
          
          1:  //qos 1st > qos 2d (next qos 1st > pre qos 2d)
          begin
            s_qos_i[0]  = 15;
            s_qos_i[1]  = 13;
          end
          
          2:  //qos 1st < qos 2d (next qos 2d < pre qos 1st)
          begin
            s_qos_i[0]  = 13;
            s_qos_i[1]  = 15;
          end
          
          3:  //qos 1st < qos 2d (next qos 2d > pre qos 1st)
          begin
            s_qos_i[0]  = 13;
            s_qos_i[1]  = 15;
          end
        endcase
      end
      else if (i != 3)
      @(posedge clk)
      begin
        case(m)
          0:
          begin
            s_data_i[0] = $urandom_range(255, 0);
          end
          
          1:
          begin
            s_data_i[0] = $urandom_range(255, 0);
          end
          
          2:
          begin
            s_data_i[1] = $urandom_range(255, 0);
          end
          
          3:
          begin
            s_data_i[1] = $urandom_range(255, 0);
          end
        endcase
      end
      else if (i == 3)
      @(posedge clk)
      begin
        case(m)
          0:
          begin
            s_data_i[0] = $urandom_range(255, 0);
            s_last_i[0] = 1;
          end
          
          1:
          begin
            s_data_i[0] = $urandom_range(255, 0);
            s_last_i[0] = 1;
          end
          
          2:
          begin
            s_data_i[1] = $urandom_range(255, 0);
            s_last_i[1] = 1;
          end
          
          3:
          begin
            s_data_i[1] = $urandom_range(255, 0);
            s_last_i[1] = 1;
          end
        endcase
      end
    end
    //second stream
    for (int j = 0; j < 4; j++)
    begin
      if      (j == 0)
      @(posedge clk)
      begin
        case(m)
          0:  //qos 1st > qos 2d (next qos 1st < pre qos 2d)
          begin
            s_data_i[0]   = $urandom_range(255, 0);
            s_valid_i[0]  = 1;
            s_qos_i[0]    = 10;
            s_last_i[0]   = 0;
          end
          
          1:  //qos 1st > qos 2d (next qos 1st > pre qos 2d)
          begin
            s_data_i[0]   = $urandom_range(255, 0);
            s_valid_i[0]  = 1;
            s_qos_i[0]    = 14;
            s_last_i[0]   = 0;
          end
          
          2:  //qos 1st < qos 2d (next qos 2d < pre qos 1st)
          begin
            s_data_i[1]   = $urandom_range(255, 0);
            s_valid_i[1]  = 1;
            s_qos_i[1]    = 10;
            s_last_i[1]   = 0;
          end
          
          3:  //qos 1st < qos 2d (next qos 2d < pre qos 1st)
          begin
            s_data_i[1]   = $urandom_range(255, 0);
            s_valid_i[1]  = 1;
            s_qos_i[1]    = 14;
            s_last_i[1]   = 0;
          end
        endcase
      end
      else if (j != 3)
      @(posedge clk)
      begin
        case(m)
          0:
          begin
            s_data_i[1] = $urandom_range(255, 0);
          end
          
          1:
          begin
            s_data_i[0] = $urandom_range(255, 0);
          end
          
          2:
          begin
            s_data_i[0] = $urandom_range(255, 0);
          end
          
          3:
          begin
            s_data_i[1] = $urandom_range(255, 0);
          end
        endcase
      end
      else if (j == 3)
      @(posedge clk)
      begin
        case(m)
          0:
          begin
            s_data_i[1] = $urandom_range(255, 0);
            s_last_i[1] = 1;
          end
          
          1:
          begin
            s_data_i[0] = $urandom_range(255, 0);
            s_last_i[0] = 1;
          end
          
          2:
          begin
            s_data_i[0] = $urandom_range(255, 0);
            s_last_i[0] = 1;
          end
          
          3:
          begin
            s_data_i[1] = $urandom_range(255, 0);
            s_last_i[1] = 1;
          end
        endcase
      end
    end
    //third stream
    for (int k = 0; k < 4; k++)
    begin
      if      (k == 0)
      @(posedge clk)
      begin
        case(m)
          0:  //qos 1st > qos 2d (next qos 1st < pre qos 2d)
          begin
            s_data_i[1]   = 0;
            s_valid_i[1]  = 0;
            s_qos_i[1]    = 0;
            s_last_i[1]   = 0;
          end
          
          1:  //qos 1st > qos 2d (next qos 1st > pre qos 2d)
          begin
            s_data_i[0]   = 0;
            s_valid_i[0]  = 0;
            s_qos_i[0]    = 0;
            s_last_i[0]   = 0;
          end
          
          2:  //qos 1st < qos 2d (next qos 2d < pre qos 1st)
          begin
            s_data_i[0]   = 0;
            s_valid_i[0]  = 0;
            s_qos_i[0]    = 0;
            s_last_i[0]   = 0;
          end
          
          3:  //qos 1st < qos 2d (next qos 2d > pre qos 1st)
          begin
            s_data_i[1]   = 0;
            s_valid_i[1]  = 0;
            s_qos_i[1]    = 0;
            s_last_i[1]   = 0;
          end
        endcase
      end
      else if (k != 3)
      @(posedge clk)
      begin
        case(m)
          0:
          begin
            s_data_i[0] = $urandom_range(255, 0);
          end
          
          1:
          begin
            s_data_i[1] = $urandom_range(255, 0);
          end
          
          2:
          begin
            s_data_i[1] = $urandom_range(255, 0);
          end
          
          3:
          begin
            s_data_i[0] = $urandom_range(255, 0);
          end
        endcase
      end
      else if (k == 3)
      @(posedge clk)
      begin
        case(m)
          0:
          begin
            s_data_i[0] = $urandom_range(255, 0);
            s_last_i[0] = 1;
          end
          
          1:
          begin
            s_data_i[1] = $urandom_range(255, 0);
            s_last_i[1] = 1;
          end
          
          2:
          begin
            s_data_i[1] = $urandom_range(255, 0);
            s_last_i[1] = 1;
          end
          
          3:
          begin
            s_data_i[0] = $urandom_range(255, 0);
            s_last_i[0] = 1;
          end
        endcase
      end
    end
    
  @(posedge clk)
  begin
    s_valid_i   = '0;
    s_last_i    = '0;
    s_data_i[0] = '0;
    s_data_i[1] = '0;
    s_qos_i[0]  = '0;
    s_qos_i[1]  = '0;
  end
    
  #100;
  end
  
  #500;
  endtask
  
  //task with the round-robin principle
  task eq_prior_stream;
  
  for(int m = 0; m < 4; m++)
  begin
    //first stream
    for (int i = 0; i < 4; i++)
    begin
      if      (i == 0)
      @(posedge clk)
      begin
        s_valid_i[0]  = 1;
        s_data_i[0]   = $urandom_range(255, 0);
        
        s_valid_i[1]  = 1;
        s_data_i[1]   = $urandom_range(255, 0);
        
        case(m)
          0:  //qos 1st is equal qos 2d
          begin
            s_qos_i[0]  = 14;
            s_qos_i[1]  = 14;
          end
          
          1:  //qos 1st is zero, qos 2d isn't zero
          begin
            s_qos_i[0]  = 0;
            s_qos_i[1]  = 14;
          end
          
          2:  //qos 1st isn't zero, qos 2d is zero
          begin
            s_qos_i[0]  = 14;
            s_qos_i[1]  = 0;
          end
          
          3:  //qos 1st is zero and qos 2d is zero
          begin
            s_qos_i[0]  = 0;
            s_qos_i[1]  = 0;
          end
        endcase
      end
      
      else if (i != 3)
      @(posedge clk)
        s_data_i[0] = $urandom_range(255, 0);
      
      else if (i == 3)
      @(posedge clk)
      begin
        s_data_i[0] = $urandom_range(255, 0);
        s_last_i[0] = 1;
      end
    end
    //second stream
    for (int j = 0; j < 4; j++)
    begin
      if      (j == 0)
      @(posedge clk)
      begin
        s_data_i[0]   = $urandom_range(255, 0);
        s_valid_i[0]  = 1;
        s_qos_i[0]    = 15;
        s_last_i[0]   = 0;
      end
      
      else if (j != 3)
      @(posedge clk)
        s_data_i[1] = $urandom_range(255, 0);
      
      else if (j == 3)
      @(posedge clk)
      begin
        s_data_i[1] = $urandom_range(255, 0);
        s_last_i[1] = 1;
      end
    end
    //third stream
    for (int k = 0; k < 4; k++)
    begin
      if      (k == 0)
      @(posedge clk)
      begin
        s_data_i[1]   = 0;
        s_valid_i[1]  = 0;
        s_qos_i[1]    = 0;
        s_last_i[1]   = 0;
      end
      
      else if (k != 3)
      @(posedge clk)
        s_data_i[0] = $urandom_range(255, 0);
      
      else if (k == 3)
      @(posedge clk)
      begin
        s_data_i[0] = $urandom_range(255, 0);
        s_last_i[0] = 1;
      end
    end
    
  @(posedge clk)
  begin
    s_valid_i   = '0;
    s_last_i    = '0;
    s_data_i[0] = '0;
    s_data_i[1] = '0;
    s_qos_i[0]  = '0;
    s_qos_i[1]  = '0;
  end
    
  #100;
  end
  
  #500;
  endtask
  
endmodule

dump.vcd
$date
	Sun Nov 19 17:55:32 2023
$end
$version
	ModelSim Version 2020.1
$end
$timescale
	1ns
$end

$scope module stream_arbiter_tb $end
$var parameter 32 ! T_DATA_WIDTH $end
$var parameter 32 " T_QOS__WIDTH $end
$var parameter 32 # STREAM_COUNT $end
$var parameter 32 $ T_ID___WIDTH $end
$var reg 1 % clk $end
$var reg 1 & rst_n $end
$var reg 2 ' s_last_i [1:0] $end
$var reg 2 ( s_valid_i [1:0] $end
$var reg 2 ) s_ready_o [1:0] $end
$var reg 8 * m_data_o [7:0] $end
$var reg 4 + m_qos_o [3:0] $end
$var reg 1 , m_id_o [0:0] $end
$var reg 1 - m_last_o $end
$var reg 1 . m_valid_o $end
$var reg 1 / m_ready_i $end

$scope task one_stream $end
$var reg 1 0 str $end
$var reg 3 1 num_pack [2:0] $end
$upscope $end

$scope task diff_qos_stream $end
$upscope $end

$scope task eq_prior_stream $end
$upscope $end

$scope module i_stream_arbiter $end
$var parameter 32 2 T_DATA_WIDTH $end
$var parameter 32 3 T_QOS__WIDTH $end
$var parameter 32 4 STREAM_COUNT $end
$var parameter 32 5 T_ID___WIDTH $end
$var wire 1 6 clk $end
$var wire 1 7 rst_n $end
$var wire 1 8 s_last_i [1] $end
$var wire 1 9 s_last_i [0] $end
$var wire 1 : s_valid_i [1] $end
$var wire 1 ; s_valid_i [0] $end
$var reg 2 < s_ready_o [1:0] $end
$var reg 8 = m_data_o [7:0] $end
$var reg 4 > m_qos_o [3:0] $end
$var reg 1 ? m_id_o [0:0] $end
$var reg 1 @ m_last_o $end
$var reg 1 A m_valid_o $end
$var wire 1 B m_ready_i $end
$var reg 2 C qos_i [1:0] $end
$var reg 2 D qos_i_d [1:0] $end
$var reg 2 E state [1:0] $end

$scope module i_prior $end
$var parameter 32 F T_QOS__WIDTH $end
$var parameter 32 G STREAM_COUNT $end
$var wire 1 : s_valid_i [1] $end
$var wire 1 ; s_valid_i [0] $end
$var reg 2 H qos_i [1:0] $end
$upscope $end
$upscope $end
$upscope $end

$scope begin std $end
$upscope $end
$enddefinitions $end
#0
$dumpvars
0%
1&
bx '
bx (
bx )
bx *
bx +
bx ,
x-
x.
x/
bx <
bx =
bx >
bx ?
x@
xA
b0 C
bx D
b0 H
bx E
x0
bx 1
b1000 !
b100 "
b10 #
b1 $
b1000 2
b100 3
b10 4
b1 5
b100 F
b10 G
06
17
x9
x8
x;
x:
xB
$end
#10
1%
16
#20
0&
0%
07
06
#30
1%
16
b0 E
0A
0@
b0 ?
b0 >
b0 =
b0 *
b0 +
b0 ,
0-
0.
b0 <
b0 )
#40
1&
b0 '
b0 (
1/
0%
17
0;
0:
09
08
1B
06
#50
00
b110 1
1%
16
b1 (
1;
b1 H
b1 C
b1 <
b1 )
b0 D
#60
0%
06
#70
1%
16
b1 E
1A
b1 D
b110000 =
b110000 *
1.
#80
0%
06
#90
1%
16
b10110101 =
b10110101 *
#100
0%
06
#110
1%
16
b10110110 =
b10110110 *
#120
0%
06
#130
1%
16
b10100 =
b10100 *
#140
0%
06
#150
1%
16
b11011111 =
b11011111 *
#160
0%
06
#170
1%
16
b1 '
19
b10111011 =
b10111011 *
#180
0%
06
#190
1%
16
b0 (
b0 '
09
0;
b0 H
b0 C
b0 <
b0 )
b0 E
1@
b0 D
b11101011 =
b11101011 *
1-
#200
0%
06
#210
1%
16
0A
0@
0-
0.
#220
0%
06
#230
1%
16
#240
0%
06
#250
1%
16
#260
0%
06
#270
1%
16
#280
0%
06
#290
10
b10 1
1%
16
b10 (
1:
b10 H
b10 C
b10 <
b10 )
#300
0%
06
#310
1%
16
b1 E
1A
b10 D
b1 ?
b1010 >
b11 =
b11 *
b1010 +
b1 ,
1.
#320
0%
06
#330
1%
16
b10 '
18
b11111100 =
b11111100 *
#340
0%
06
#350
1%
16
b0 (
b0 '
08
0:
b0 H
b0 C
b0 <
b0 )
b0 E
1@
b0 D
b1011101 =
b1011101 *
1-
#360
0%
06
#370
1%
16
0A
0@
0-
0.
#380
0%
06
#390
1%
16
#400
0%
06
#410
1%
16
#420
0%
06
#430
1%
16
#440
0%
06
#450
b100 1
1%
16
b10 (
1:
b10 H
b10 C
b10 <
b10 )
#460
0%
06
#470
1%
16
b1 E
1A
b10 D
b110 >
b111111 =
b111111 *
b110 +
1.
#480
0%
06
#490
1%
16
b100011 =
b100011 *
#500
0%
06
#510
1%
16
b10101000 =
b10101000 *
#520
0%
06
#530
1%
16
b10 '
18
b10010000 =
b10010000 *
#540
0%
06
#550
1%
16
b0 (
b0 '
08
0:
b0 H
b0 C
b0 <
b0 )
b0 E
1@
b0 D
b100101 =
b100101 *
1-
#560
0%
06
#570
1%
16
0A
0@
0-
0.
#580
0%
06
#590
1%
16
#600
0%
06
#610
1%
16
#620
0%
06
#630
1%
16
#640
0%
06
#650
00
b101 1
1%
16
b1 (
1;
b1 H
b1 C
b1 <
b1 )
#660
0%
06
#670
1%
16
b1 E
1A
b1 D
b0 ?
b10 >
b110001 =
b110001 *
b10 +
b0 ,
1.
#680
0%
06
#690
1%
16
b11001101 =
b11001101 *
#700
0%
06
#710
1%
16
b1100100 =
b1100100 *
#720
0%
06
#730
1%
16
b101011 =
b101011 *
#740
0%
06
#750
1%
16
b1 '
19
b11101010 =
b11101010 *
#760
0%
06
#770
1%
16
b0 (
b0 '
09
0;
b0 H
b0 C
b0 <
b0 )
b0 E
1@
b0 D
b10010001 =
b10010001 *
1-
#780
0%
06
#790
1%
16
0A
0@
0-
0.
#800
0%
06
#810
1%
16
#820
0%
06
#830
1%
16
#840
0%
06
#850
1%
16
#860
0%
06
#870
b10 1
1%
16
b1 (
1;
b1 H
b1 C
b1 <
b1 )
#880
0%
06
#890
1%
16
b1 E
1A
b1 D
b101 >
b1110110 =
b1110110 *
b101 +
1.
#900
0%
06
#910
1%
16
b1 '
19
b10111000 =
b10111000 *
#920
0%
06
#930
1%
16
b0 (
b0 '
09
0;
b0 H
b0 C
b0 <
b0 )
b0 E
1@
b0 D
b10100 =
b10100 *
1-
#940
0%
06
#950
1%
16
0A
0@
0-
0.
#960
0%
06
#970
1%
16
#980
0%
06
#990
1%
16
#1000
0%
06
#1010
1%
16
#1020
0%
06
#1030
10
b101 1
1%
16
b10 (
1:
b10 H
b10 C
b10 <
b10 )
#1040
0%
06
#1050
1%
16
b1 E
1A
b10 D
b1 ?
b1101 >
b10000010 =
b10000010 *
b1101 +
b1 ,
1.
#1060
0%
06
#1070
1%
16
b11011001 =
b11011001 *
#1080
0%
06
#1090
1%
16
b10100 =
b10100 *
#1100
0%
06
#1110
1%
16
b1111101 =
b1111101 *
#1120
0%
06
#1130
1%
16
b10 '
18
b10001100 =
b10001100 *
#1140
0%
06
#1150
1%
16
b0 (
b0 '
08
0:
b0 H
b0 C
b0 <
b0 )
b0 E
1@
b0 D
b1001011 =
b1001011 *
1-
#1160
0%
06
#1170
1%
16
0A
0@
0-
0.
#1180
0%
06
#1190
1%
16
#1200
0%
06
#1210
1%
16
#1220
0%
06
#1230
1%
16
#1240
0%
06
#1250
1%
16
b1 (
b11 (
1;
1:
b1 H
b1 C
b1 <
b1 )
#1260
0%
06
#1270
1%
16
b1 E
1A
b1 D
b0 ?
b1111 >
b1111100 =
b1111100 *
b1111 +
b0 ,
1.
#1280
0%
06
#1290
1%
16
b10100000 =
b10100000 *
#1300
0%
06
#1310
1%
16
b1 '
19
b1001100 =
b1001100 *
#1320
0%
06
#1330
1%
16
b0 '
09
b0 H
b10 H
b10 C
b10 <
b10 )
b0 E
1@
b0 D
b1100001 =
b1100001 *
1-
b0 <
b10 <
#1340
0%
06
#1350
1%
16
b1 E
0@
b10 D
b1 ?
b1101 >
b1110000 =
b1110000 *
b1101 +
b1 ,
0-
#1360
0%
06
#1370
1%
16
b11101 =
b11101 *
#1380
0%
06
#1390
1%
16
b10 '
18
b10110 =
b10110 *
#1400
0%
06
#1410
1%
16
b1 (
b0 '
08
0:
b0 H
b1 H
b1 C
b1 <
b1 )
b0 E
1@
b0 D
b10111001 =
b10111001 *
1-
b0 <
b1 <
#1420
0%
06
#1430
1%
16
b1 E
0@
b1 D
b0 ?
b1010 >
b10011101 =
b10011101 *
b1010 +
b0 ,
0-
#1440
0%
06
#1450
1%
16
b1110010 =
b1110010 *
#1460
0%
06
#1470
1%
16
b1 '
19
b10010011 =
b10010011 *
#1480
0%
06
#1490
1%
16
b0 (
b0 '
09
0;
b0 H
b0 C
b0 <
b0 )
b0 E
1@
b0 D
b1000101 =
b1000101 *
1-
#1500
0%
06
#1510
1%
16
0A
0@
0-
0.
#1520
0%
06
#1530
1%
16
#1540
0%
06
#1550
1%
16
#1560
0%
06
#1570
1%
16
#1580
0%
06
#1590
1%
16
b1 (
b11 (
1;
1:
b1 H
b1 C
b1 <
b1 )
#1600
0%
06
#1610
1%
16
b1 E
1A
b1 D
b1111 >
b1001110 =
b1001110 *
b1111 +
1.
#1620
0%
06
#1630
1%
16
b11100110 =
b11100110 *
#1640
0%
06
#1650
1%
16
b1 '
19
b1111000 =
b1111000 *
#1660
0%
06
#1670
1%
16
b0 '
09
b0 H
b1 H
b0 E
1@
b0 D
b11010111 =
b11010111 *
1-
b0 <
b1 <
#1680
0%
06
#1690
1%
16
b1 E
0@
b1 D
b1110 >
b1100111 =
b1100111 *
b1110 +
0-
#1700
0%
06
#1710
1%
16
b1100011 =
b1100011 *
#1720
0%
06
#1730
1%
16
b1 '
19
b101 =
b101 *
#1740
0%
06
#1750
1%
16
b10 (
b0 '
09
0;
b0 H
b10 H
b10 C
b10 <
b10 )
b0 E
1@
b0 D
b10101000 =
b10101000 *
1-
b0 <
b10 <
#1760
0%
06
#1770
1%
16
b1 E
0@
b10 D
b1 ?
b1101 >
b110101 =
b110101 *
b1101 +
b1 ,
0-
#1780
0%
06
#1790
1%
16
b11000001 =
b11000001 *
#1800
0%
06
#1810
1%
16
b10 '
18
b10111111 =
b10111111 *
#1820
0%
06
#1830
1%
16
b0 (
b0 '
08
0:
b0 H
b0 C
b0 <
b0 )
b0 E
1@
b0 D
b10001000 =
b10001000 *
1-
#1840
0%
06
#1850
1%
16
0A
0@
0-
0.
#1860
0%
06
#1870
1%
16
#1880
0%
06
#1890
1%
16
#1900
0%
06
#1910
1%
16
#1920
0%
06
#1930
1%
16
b1 (
b11 (
1;
1:
b10 H
b10 C
b10 <
b10 )
#1940
0%
06
#1950
1%
16
b1 E
1A
b10 D
b1111 >
b11001100 =
b11001100 *
b1111 +
1.
#1960
0%
06
#1970
1%
16
b1001100 =
b1001100 *
#1980
0%
06
#1990
1%
16
b10 '
18
b1100 =
b1100 *
#2000
0%
06
#2010
1%
16
b0 '
08
b0 H
b1 H
b1 C
b1 <
b1 )
b0 E
1@
b0 D
b10111001 =
b10111001 *
1-
b0 <
b1 <
#2020
0%
06
#2030
1%
16
b1 E
0@
b1 D
b0 ?
b1101 >
b10101100 =
b10101100 *
b1101 +
b0 ,
0-
#2040
0%
06
#2050
1%
16
b11111010 =
b11111010 *
#2060
0%
06
#2070
1%
16
b1 '
19
b11100 =
b11100 *
#2080
0%
06
#2090
1%
16
b10 (
b0 '
09
0;
b0 H
b10 H
b10 C
b10 <
b10 )
b0 E
1@
b0 D
b10010011 =
b10010011 *
1-
b0 <
b10 <
#2100
0%
06
#2110
1%
16
b1 E
0@
b10 D
b1 ?
b1010 >
b1110011 =
b1110011 *
b1010 +
b1 ,
0-
#2120
0%
06
#2130
1%
16
b11110111 =
b11110111 *
#2140
0%
06
#2150
1%
16
b10 '
18
b10001010 =
b10001010 *
#2160
0%
06
#2170
1%
16
b0 (
b0 '
08
0:
b0 H
b0 C
b0 <
b0 )
b0 E
1@
b0 D
b11110101 =
b11110101 *
1-
#2180
0%
06
#2190
1%
16
0A
0@
0-
0.
#2200
0%
06
#2210
1%
16
#2220
0%
06
#2230
1%
16
#2240
0%
06
#2250
1%
16
#2260
0%
06
#2270
1%
16
b1 (
b11 (
1;
1:
b10 H
b10 C
b10 <
b10 )
#2280
0%
06
#2290
1%
16
b1 E
1A
b10 D
b1111 >
b1000000 =
b1000000 *
b1111 +
1.
#2300
0%
06
#2310
1%
16
b10101001 =
b10101001 *
#2320
0%
06
#2330
1%
16
b10 '
18
b101110 =
b101110 *
#2340
0%
06
#2350
1%
16
b0 '
08
b0 H
b10 H
b0 E
1@
b0 D
b10111010 =
b10111010 *
1-
b0 <
b10 <
#2360
0%
06
#2370
1%
16
b1 E
0@
b10 D
b1110 >
b11011001 =
b11011001 *
b1110 +
0-
#2380
0%
06
#2390
1%
16
b10111011 =
b10111011 *
#2400
0%
06
#2410
1%
16
b10 '
18
b1011110 =
b1011110 *
#2420
0%
06
#2430
1%
16
b1 (
b0 '
08
0:
b0 H
b1 H
b1 C
b1 <
b1 )
b0 E
1@
b0 D
b100101 =
b100101 *
1-
b0 <
b1 <
#2440
0%
06
#2450
1%
16
b1 E
0@
b1 D
b0 ?
b1101 >
b1110100 =
b1110100 *
b1101 +
b0 ,
0-
#2460
0%
06
#2470
1%
16
b100 =
b100 *
#2480
0%
06
#2490
1%
16
b1 '
19
b101111 =
b101111 *
#2500
0%
06
#2510
1%
16
b0 (
b0 '
09
0;
b0 H
b0 C
b0 <
b0 )
b0 E
1@
b0 D
b10010100 =
b10010100 *
1-
#2520
0%
06
#2530
1%
16
0A
0@
0-
0.
